mattplottslib/__init__.py
mattplottslib/plot.py
mattplottslib-0.0.5.dist-info/METADATA
mattplottslib-0.0.5.dist-info/WHEEL
mattplottslib-0.0.5.dist-info/top_level.txt
mattplottslib-0.0.5.dist-info/RECORD
