Metadata-Version: 2.4
Name: mattplottslib
Version: 0.0.5
Summary: package description
Author-email: Matthew Potts <matthew-potts@live.com>
Requires-Python: >=3.7
